<?xml version="1.0"?>
<ServerSettings>
  <property name="ServerPort" value="26900"/>	<!-- Port you want the server to listen on. -->
  <property name="ServerIsPublic" value="true"/>  <!-- Should this server register to master server -->
  <property name="ServerName" value="My Game Host"/>	<!-- Whatever you want the name to be. -->
  <property name="ServerPassword" value=""/>	<!-- Password to gain entry to the server -->
  <property name="ServerMaxPlayerCount" value="8"/> <!-- Maximum Concurrent Players -->
  <property name="ServerDescription" value="A 7 Days to Die server"/> <!-- Whatever you want the description to be. -->
  <property name="ServerWebsiteURL" value=""/>	<!-- Website URL for the server -->

  <property name="HideCommandExecutionLog" value="true"/>	<!-- disable printing of command execution to the server log -->
  <property name="MaxUncoveredMapChunksPerPlayer" value="4"/>	<!-- Limit of per player uncovered map area configurable, client side defaults to 4 times the area of before A16 (128 km² instead of 32 km²) -->
  <property name="ServerReservedSlots" value="1"/>	<!-- allows admins to join a full server by reserving a slot -->

  <property name="GameWorld" value="Navezgane"/>   <!-- Navezgane, MP Wasteland Horde, MP Wasteland Skirmish, MP Wasteland War, Random Gen -->
  <property name="GameName" value="My Game"/>	<!-- Whatever you want the game name to be THIS CONTROLS THE RANDOM GENERATION SEED -->
  <property name="GameDifficulty" value="2"/>  	<!-- 0 - 4, 0=easiest, 4=hardest -->
  <property name="GameMode" value="GameModeSurvivalMP"/>   <!-- GameModeSurvivalMP, GameModeSurvivalSP (MP has land protection) -->
  <property name="PlayerKillingMode" value="3" />   <!-- Player Killing Settings (0 = No Killing, 1 = Kill Allies Only, 2 = Kill Strangers Only, 3 = Kill Everyone) --> 

  <property name="ZombiesRun" value="0" />   <!-- 0 = default day/night walk/run, 1 = never run, 2 = always run -->
  <property name="BuildCreate" value="false" />	  <!-- cheat mode on/off -->
  <property name="DayNightLength" value="40" />	  <!-- 40 minutes -->
  <property name="FriendlyFire" value="false" />   <!-- Can friendly players damage each other (PvP) -->
  <property name="PersistentPlayerProfiles" value="true" />   <!-- If disabled a player can join with any selected profile. If true they will join with the last profile they joined with -->

  <property name="ControlPanelEnabled" value="false"/>	 <!-- Enable/Disable the control panel -->
  <property name="ControlPanelPort" value="8080"/>   <!-- Port of the control panel webpage -->
  <property name="ControlPanelPassword" value="{RANDOM PASSWORD}"/>   <!-- Password to gain entry to the control panel -->

  <property name="TelnetEnabled" value="false"/>	  <!-- Enable/Disable the telnet -->
  <property name="TelnetPort" value="8081"/>	<!-- Port of the telnet server -->
  <property name="TelnetPassword" value="{RANDOM PASSWORD}"/>	<!-- Password to gain entry to telnet interface -->

  <property name="DisableNAT" value="true"/>  <!-- set this to true if your router doesn't support NAT -->
  <property name="AdminFileName" value="serveradmin.xml"/>  <!-- Server admin file name -->

  <property name="DropOnDeath" value="0" />   <!-- 0 = everything, 1 = toolbelt only, 2 = backpack only, 3 = delete all -->
  <property name="DropOnQuit" value="1" />   <!-- 0 = nothing, 1 = everything, 2 = toolbelt only, 3 = backpack only -->

  <property name="CraftTimer" value="1" />   <!-- 0 = None (instant), 1 = Normal, 2 = Fast (double speed) -->
  <property name="LootTimer" value="1" />   <!-- 0 = None (instant), 1 = Normal, 2 = Fast (double speed) -->

  <property name="EnemySpawnMode" value="true" />	  <!-- true or false, false will prevent zombies from spawning -->
  <property name="EnemyDifficulty" value="0" />	  <!-- 0 = Normal, 1 = Feral -->
  <property name="BloodMoonEnemyCount" value="100" />	  <!-- Adjust this to get more enemies per player on blood-moons if your game stage is high enough. Game-stages are still determined by your party -->
  <property name="BedrollDeadZoneSize" value="10" />	  <!-- This is a 3 dimensional unit in meters from bedrolls that blocks zombie spawning.  Including zombies spawned from biomes, screamer hordes, blood moon hordes and even sleeper volumes that are within this distance. -->

  <property name="BlockDurabilityModifier" value="100" />    <!-- percentage in whole numbers -->

  <property name="LootAbundance" value="100" />    <!-- percentage in whole numbers -->
  <property name="LootRespawnDays" value="7" />    <!-- days in whole numbers -->

  <property name="LandClaimSize" value="7"/>   <!-- Size in blocks that is protected by a keystone -->
  <property name="LandClaimDeadZone" value="30"/>   <!-- Keystones must be this many blocks apart (unless you are friends with the other player) -->
  <property name="LandClaimExpiryTime" value="3"/>   <!-- The number of days a player can be offline before their claims expire and are no longer protected -->
  <property name="LandClaimDecayMode" value="0"/>   <!-- Controls how offline players land claims decay. All claims have full protection for the first 24hrs. 0=Linear, 1=Exponential, 2=Full protection until claim is expired. -->
  <property name="LandClaimOnlineDurabilityModifier" value="4"/>    <!-- How much protected claim area block hardness is increased when a player is online. 0 means infinite (no damage will ever be taken). Default is 32x -->
  <property name="LandClaimOfflineDurabilityModifier" value="4"/>   <!-- How much protected claim area block hardness is increased when a player is offline. 0 means infinite (no damage will ever be taken). Default is 32x -->
  <property name="AirDropFrequency" value="72"/>    <!-- How often airdrop occur in game-hours, 0 == never -->
  <property name="AirDropMarker" value="true"/>    <!-- show the air drops on the map true/false -->  

  <property name="MaxSpawnedZombies" value="60"/>    <!-- Making this number too large (more than about 80) may cause servers to run at poor framerates which will effect lag and play quality for clients. -->
  <property name="EACEnabled" value="true"/>  <!-- Enables/Disables EasyAntiCheat -->
 <!-- <property name="ServerDisabledNetworkProtocols" value=""/> --> <!-- comma separated list of networking protocols not to be used. Possible values: unet, raknet, steamnetworking -->

  <!--property name="SaveGameFolder" value="absolute path" /-->	<!-- use this to override the default save game path -->
</ServerSettings>